LICENSE
README.md
setup.py
META_TOOLBOX/META.py
META_TOOLBOX/META_CO_LIBRARY.py
META_TOOLBOX/META_DE_LIBRARY.py
META_TOOLBOX/META_FA_LIBRARY.py
META_TOOLBOX/META_FUNCTIONS.py
META_TOOLBOX/META_GA_LIBRARY.py
META_TOOLBOX/META_GRAPHICS_LIBRARY.py
META_TOOLBOX/META_HC_LIBRARY.py
META_TOOLBOX/META_KNAPSACK.py
META_TOOLBOX/META_PORTIFOLIO.py
META_TOOLBOX/META_PSO_LIBRARY.py
META_TOOLBOX/META_SA_LIBRARY.py
META_TOOLBOX/__init__.py
META_TOOLBOX.egg-info/PKG-INFO
META_TOOLBOX.egg-info/SOURCES.txt
META_TOOLBOX.egg-info/dependency_links.txt
META_TOOLBOX.egg-info/requires.txt
META_TOOLBOX.egg-info/top_level.txt