Metadata-Version: 2.1
Name: META-TOOLBOX
Version: 2023.3
Summary: The METApy optimization toolbox is an easy of use environment for applying metaheuristic optimization methods. The platform has several optimization methods, as well as functions for generating charts and statistical analysis of the results.
Home-page: https://wmpjrufg.github.io/META_TOOLBOX/
Author-email: wanderlei_junior@ufcat.edu.br
License: Apache License
Platform: UNKNOWN
Classifier: Programming Language :: Python
Classifier: Topic :: Scientific/Engineering :: Mathematics
Classifier: Topic :: Scientific/Engineering
License-File: LICENSE
